condascan/__init__.py
condascan/cache.py
condascan/cli.py
condascan/codes.py
condascan/display.py
condascan/parser.py
condascan/task.py
condascan-1.0.0.dist-info/licenses/LICENSE
condascan-1.0.0.dist-info/METADATA
condascan-1.0.0.dist-info/WHEEL
condascan-1.0.0.dist-info/entry_points.txt
condascan-1.0.0.dist-info/top_level.txt
condascan-1.0.0.dist-info/RECORD
