Metadata-Version: 2.4
Name: condascan
Version: 1.0.0
Summary: CLI tool to look for the best conda environment which satisfies certain requirements
Author-email: Steve Immanuel <iam.steve.immanuel@gmail.com>
License: MIT License
Project-URL: Homepage, https://github.com/SteveImmanuel/condascan
Keywords: conda,anaconda,miniconda
Classifier: License :: OSI Approved :: MIT License
Classifier: Programming Language :: Python :: 3
Classifier: Operating System :: OS Independent
Requires-Python: >=3.8
License-File: LICENSE
Requires-Dist: rich
Requires-Dist: packaging>=25.0
Requires-Dist: pyyaml
Provides-Extra: dev
Requires-Dist: pytest; extra == "dev"
Requires-Dist: bumpver; extra == "dev"
Dynamic: license-file
